README.md
setup.py
platform_sdk/__init__.py
platform_sdk/clients/__init__.py
platform_sdk/clients/central_client.py
platform_sdk/clients/events_client.py
platform_sdk/clients/identity_client.py
platform_sdk/clients/jira_service_management_client.py
platform_sdk/clients/mapper_client.py
platform_sdk/clients/ods_client.py
platform_sdk/clients/oneroster_authentication.py
platform_sdk/clients/oneroster_client.py
platform_sdk/clients/slack.py
platform_sdk/clients/user_creation.py
platform_sdk/helpers/__init__.py
platform_sdk/helpers/exception_logger.py
platform_sdk/helpers/link_header.py
platform_sdk/helpers/sentry.py
platform_sdk/models/__init__.py
platform_sdk/models/cloud_event.py
platform_sdk/models/domain.py
platform_sdk/models/link_header.py
platform_sdk/models/partner.py
platform_sdk/models/user.py
platform_sdk/shared/__init__.py
platform_sdk/shared/constants.py
platform_sdk/shared/exceptions.py
platform_sdk/shared/lti_helper.py
platform_sdk/shared/utilities.py
strongmind_platform_sdk.egg-info/PKG-INFO
strongmind_platform_sdk.egg-info/SOURCES.txt
strongmind_platform_sdk.egg-info/dependency_links.txt
strongmind_platform_sdk.egg-info/requires.txt
strongmind_platform_sdk.egg-info/top_level.txt
test/__init__.py
test/test_events_client.py
test/test_exception_logger.py
test/test_identity_client.py
test/test_jira_service_management_client.py
test/test_link_header.py
test/test_ods_client.py
test/test_ods_client_enrollment_filtering.py
test/test_oneroster_authentication.py
test/test_oneroster_client.py
test/test_sentry.py
test/test_slack_client.py
test/test_user_creation_client.py
test/factories/__init__.py
test/factories/domain_factory.py
test/factories/event_factories.py
test/factories/oneroster_academic_session.py
test/factories/oneroster_class.py
test/factories/oneroster_course.py
test/factories/oneroster_enrollment.py
test/factories/oneroster_guidref.py
test/factories/oneroster_lineitem.py
test/factories/oneroster_org_factory.py
test/factories/oneroster_result.py
test/factories/oneroster_user.py
test/factories/oneroster_user_id.py
test/factories/partner.py
test/factories/response_factory.py
test/factories/standalone_partner.py
test/factories/user_factories.py