Metadata-Version: 2.4
Name: strongmind-platform-sdk
Version: 3.9.3
Summary: Common utilities, models, and clients used with StrongMind Platform APIs
Home-page: https://github.com/StrongMind/platform-python-sdk
Author: Team Platform
Author-email: platform@strongmind.com
Requires-Python: >=3.7
Requires-Dist: pytz
Requires-Dist: strongmind-oneroster-client>=2.0.3
Requires-Dist: pydantic>=1.10.11
Requires-Dist: cryptography>=37.0.4
Requires-Dist: sentry-sdk
Dynamic: author
Dynamic: author-email
Dynamic: description
Dynamic: description-content-type
Dynamic: home-page
Dynamic: requires-dist
Dynamic: requires-python
Dynamic: summary
